<?xml version="1.0" encoding="UTF-8"?>
<objects serializationModel="Studio.02.02.00">
	<object class="AudioFile" id="{d1efdc36-7de2-4b30-aa1f-6d99e616dffa}">
		<property name="assetPath">
			<value>Vehicles/AccelNormal.ry.32.wav</value>
		</property>
		<property name="frequencyInKHz">
			<value>32</value>
		</property>
		<property name="channelCount">
			<value>1</value>
		</property>
		<property name="length">
			<value>9.3375937499999999</value>
		</property>
		<relationship name="masterAssetFolder">
			<destination>{a9623d1e-a735-4ba1-8e9f-078811bde515}</destination>
		</relationship>
	</object>
</objects>
